{
  "localizedName": "Italy (IT)",
  "pluginVersion": "2.1.3",
  "authors": "gabry",
  "generalNotAuthenticated": "Non sei registrato o hai già effettuato l'accesso!",
  "generalNotLoggedIn": "Non hai ancora effettuato l'accesso!",
  "generalPasswordLength": "La lunghezza della password deve essere compresa tra %min% e %max% caratteri!",
  "generalUnknownHash": "Il tuo account usa un algoritmo sconosciuto, per favore segnala questo problema ad un admin.",
  "loginTriesExceeded": "Hai superato il numero massimo di tentativi per il login (%max%).",
  "loginFail": "Accesso negato! Password errata!",
  "loginSuccess": "Login eseguito con successo!",
  "changeFail": "Impossibile effettuare l'operazione: password non valida!",
  "changeSuccess": "Password modificata correttamente!",
  "logoutFail": "Impossibile uscire! Errore %error%",
  "logoutSuccess": "Logout effettuato!",
  "registerAlready": "Sei già registrato con questo account!",
  "registerCaptcha": "Per favore, inserisci il captcha in chat!",
  "registerSuccess": "Registrato correttamente, adesso hai effettuato l'accesso.",
  "commandError": "Errore durante l'esecuzione del comando: %error%",
  "commandUnknown": "Comando sconosciuto! Usa %cmd% per aiuto.",
  "commandArguments": "Argomenti insufficienti. Usa %cmd% per aiuto.",
  "lacHelp": "Mostra comando aiuto",
  "lacRmpass": "Rimuove la password di un utente",
  "lacRmpassArgs": "<username>",
  "lacNotRegistered": "Nessun giocatore si è registrato con questo nome utente!",
  "lacResetPlayer": "Account resettato correttamente!",
  "lacImport": "Importa da un altro database",
  "lacImportArgs": "<sorgente> [argomenti]",
  "lacUnknownSource": "Tipo di database sconosciuto, per favore, consulta la wiki!",
  "lacImportFailed": "Impossibile importare, per favore, consulta il log!",
  "sessionContinue": "La tua ultima sessione continua da %sec% secondi.",
  "messageLogin": "Per favore, accedi utilizzando /login <password>",
  "messageRegister": "Per favore, registrati utilizzando /register <password>",
  "errorRefreshProfile": "Il tuo account è stato modificato, per favore, riaccedi!",
  "errorNotRegistered": "Utente non registrato!",
  "kickAlreadyOnline": "Un giocatore con lo stesso username è già online, riprova!",
  "kickUsernameChars": "Il tuo username contiene caratteri non consentiti!",
  "kickUsernameLength": "Il tuo username è troppo lungo/corto (%min% - %max% caratteri)",
  "kickTimeOut": "Tempo per il login scaduto, riprova!"
}
