{
  "localizedName": "中文 (臺灣)",
  "pluginVersion": "2.1.3",
  "authors": "Small_Ku",
  "generalNotAuthenticated": "\u4f60\u4ecd\u672a\u8a3b\u518a\u6216\u767b\u5165!",
  "generalNotLoggedIn": "\u4f60\u5c1a\u672a\u767b\u5165!",
  "generalPasswordLength": "\u5bc6\u78bc\u9577\u5ea6\u5fc5\u9808\u5728 %min% \u5b57\u81f3 %max% \u5b57\u4e4b\u9593!",
  "generalUnknownHash": "你的賬戶正使用一個不明的散列算法, 請向管理員報告此錯誤.",
  "loginTriesExceeded": "\u8d85\u8d8a\u6700\u5927\u5617\u8a66\u767b\u5165\u6b21\u6578: %max%",
  "loginFail": "\u767b\u5165\u5931\u6557! \u7121\u6548\u5bc6\u78bc",
  "loginSuccess": "\u6210\u529f\u767b\u5165.",
  "changeFail": "不能更改密碼, 密碼無效!",
  "changeSuccess": "成功更改密碼!",
  "logoutFail": "不能登出! %error%",
  "logoutSuccess": "你已成功登出!",
  "registerAlready": "\u4f60\u8a3b\u518a\u904e\u4e86!",
  "registerCaptcha": "請在對話欄輸入地圖上的驗證碼!",
  "registerSuccess": "\u6210\u529f\u8a3b\u518a,\u4f60\u5df2\u767b\u5165.",
  "commandError": "執行指令時出現錯誤: %error%",
  "commandUnknown": "未知指令! 使用 %cmd% 取得幫助.",
  "commandArguments": "參數不足! 使用 %cmd% 取得幫助.",
  "lacHelp": "顯示幫助",
  "lacRmpass": "移除用戶密碼",
  "lacRmpassArgs": "<用戶名稱>",
  "lacNotRegistered": "未有這個名字的玩家註冊!",
  "lacResetPlayer": "成功重設玩家賬戶!",
  "lacImport": "從其他數據庫導入",
  "lacImportArgs": "<來源> [參數]",
  "lacUnknownSource": "未知數據類型, 請查看插件維基!",
  "lacImportFailed": "無法執行導入, 請查看記錄!",
  "sessionContinue": "\u4f60\u6700\u5f8c\u4e00\u6b21\u767b\u5165\u5df2\u5728 %sec% \u4e4b\u524d.",
  "messageLogin": "\u8acb\u4f7f\u7528 /login <\u5bc6\u78bc> \u767b\u5165",
  "messageRegister": "\u8acb\u4f7f\u7528 /register <\u5bc6\u78bc> \u8a3b\u518a",
  "errorRefreshProfile": "\u4f60\u7684\u8cec\u6236\u5df2\u88ab\u7b2c\u4e09\u65b9\u66f4\u6539, \u8acb\u91cd\u65b0\u52a0\u5165\u4f3a\u670d\u5668!",
  "errorNotRegistered": "\u7528\u6236\u5c1a\u672a\u8a3b\u518a!",
  "kickAlreadyOnline": "\u9019\u500b\u7528\u6236\u5df2\u7d93\u4e0a\u7dda!",
  "kickUsernameChars": "\u4f60\u7684\u7528\u6236\u540d\u7a31\u5305\u542b\u975e\u6cd5\u5b57\u5143!",
  "kickUsernameLength": "\u4f60\u7684\u7528\u6236\u540d\u7a31\u904e\u9577/\u904e\u77ed! (%min% - %max% \u5b57)",
  "kickTimeOut": "\u767b\u5165\u903e\u6642!"
}
